bmiroger/__init__.py
bmiroger/_version.py
bmiroger/bmi_roger.py
roger/__init__.py
roger/_version.py
roger/backend.py
roger/distributed.py
roger/logs.py
roger/lookuptables.py
roger/plugins.py
roger/progress.py
roger/restart.py
roger/roger.py
roger/routines.py
roger/runtime.py
roger/settings.py
roger/signals.py
roger/state.py
roger/time.py
roger/timer.py
roger/variables.py
roger/bmimodels/__init__.py
roger/bmimodels/oneD/__init__.py
roger/bmimodels/oneD/oneD.py
roger/bmimodels/oneD_crop/__init__.py
roger/bmimodels/oneD_crop/oneD_crop.py
roger/bmimodels/svat/__init__.py
roger/bmimodels/svat/svat.py
roger/bmimodels/svat_crop/__init__.py
roger/bmimodels/svat_crop/svat_crop.py
roger/cli/__init__.py
roger/cli/roger.py
roger/cli/roger_copy_model.py
roger/cli/roger_create_mask.py
roger/cli/roger_resubmit.py
roger/cli/roger_run.py
roger/cli/roger_run_base.py
roger/core/__init__.py
roger/core/adaptive_time_stepping.py
roger/core/capillary_rise.py
roger/core/crop.py
roger/core/evapotranspiration.py
roger/core/film_flow.py
roger/core/groundwater.py
roger/core/groundwater_flow.py
roger/core/infiltration.py
roger/core/interception.py
roger/core/nitrate.py
roger/core/numerics.py
roger/core/operators.py
roger/core/root_zone.py
roger/core/sas.py
roger/core/snow.py
roger/core/soil.py
roger/core/subsoil.py
roger/core/subsurface_runoff.py
roger/core/surface.py
roger/core/surface_runoff.py
roger/core/transport.py
roger/core/utilities.py
roger/diagnostics/__init__.py
roger/diagnostics/api.py
roger/diagnostics/average.py
roger/diagnostics/base.py
roger/diagnostics/collect.py
roger/diagnostics/constant.py
roger/diagnostics/maximum.py
roger/diagnostics/minimum.py
roger/diagnostics/rate.py
roger/diagnostics/snapshot.py
roger/diagnostics/tracer_monitor.py
roger/diagnostics/water_monitor.py
roger/io_tools/__init__.py
roger/io_tools/csv.py
roger/io_tools/hdf5.py
roger/io_tools/netcdf.py
roger/io_tools/yml.py
roger/look_up_tables/_crop_parameters.csv
roger/look_up_tables/crop_parameters.csv
roger-3.0.9.dist-info/LICENSE
roger-3.0.9.dist-info/METADATA
roger-3.0.9.dist-info/WHEEL
roger-3.0.9.dist-info/entry_points.txt
roger-3.0.9.dist-info/top_level.txt
roger-3.0.9.dist-info/RECORD
