Metadata-Version: 2.2
Name: roger
Version: 3.0.9
Summary: Runoff Generation Research - a process-based hydrological toolbox model in Python
Home-page: https://roger.readthedocs.io
Author: Robin Schwemmle (University of Freiburg)
Author-email: robin.schwemmle@hydrology.uni-freiburg.de
License: MIT
Keywords: hydrology python parallel numpy multi-core geophysics hydrologic-model gpu jax
Classifier: Development Status :: 4 - Beta
Classifier: Intended Audience :: Science/Research
Classifier: License :: OSI Approved :: MIT License
Classifier: Programming Language :: Python :: 3
Classifier: Programming Language :: Python :: 3.7
Classifier: Programming Language :: Python :: 3.8
Classifier: Programming Language :: Python :: 3.9
Classifier: Programming Language :: Python :: 3.10
Classifier: Programming Language :: Python :: 3.11
Classifier: Programming Language :: Python :: Implementation :: CPython
Classifier: Topic :: Scientific/Engineering
Classifier: Operating System :: Microsoft :: Windows
Classifier: Operating System :: POSIX
Classifier: Operating System :: Unix
Classifier: Operating System :: MacOS
Requires-Python: >=3.7
License-File: LICENSE
Requires-Dist: bmipy<=2.0.1
Requires-Dist: cftime<=1.6.3
Requires-Dist: click<=8.1.7
Requires-Dist: cython<=3.0.10
Requires-Dist: entrypoints<=0.4
Requires-Dist: h5netcdf<=1.3.0
Requires-Dist: h5py<=3.11.0
Requires-Dist: loguru<=0.7.2
Requires-Dist: matplotlib<=3.8.4
Requires-Dist: numpy<=1.26.4,>=1.13
Requires-Dist: pandas<=2.2.2
Requires-Dist: pyyaml<=6.0.1
Requires-Dist: scipy<=1.13.1
Requires-Dist: seaborn<=0.13.2
Requires-Dist: tqdm<=4.66.4
Provides-Extra: test
Requires-Dist: pytest; extra == "test"
Requires-Dist: pytest-cov; extra == "test"
Requires-Dist: pytest-forked; extra == "test"
Requires-Dist: codecov; extra == "test"
Requires-Dist: xarray; extra == "test"
Provides-Extra: jax
Requires-Dist: jaxlib<=0.4.28; extra == "jax"
Requires-Dist: jax<=0.4.28,>=0.2.10; extra == "jax"
Dynamic: author
Dynamic: author-email
Dynamic: classifier
Dynamic: description
Dynamic: description-content-type
Dynamic: home-page
Dynamic: keywords
Dynamic: license
Dynamic: provides-extra
Dynamic: requires-dist
Dynamic: requires-python
Dynamic: summary
